{"cameraMode":{"drawMode":0,"name":"Shaded","section":"Shading Mode"},"sceneLighting":true,"audioPlay":false,"sceneViewState":{"m_AlwaysRefresh":false,"showFog":true,"showSkybox":true,"showFlares":true,"showImageEffects":true,"showParticleSystems":true,"showVisualEffectGraphs":true,"m_FxEnabled":true},"in2DMode":false,"pivot":{"x":4.544764041900635,"y":4.074840068817139,"z":-5.522853851318359},"rotation":{"x":0.25231510400772097,"y":-0.3962252736091614,"z":0.1147036924958229,"w":0.8754452466964722},"size":1.9899749755859376,"orthographic":false}